{
  "resources": [],
  "spritemap": {
    "/music/OK KO_Music_LOOP": {
      "start": 0,
      "end": 82.56,
      "loop": false
    },
    "/sfx_Coin_Pick_Up/sfx_Coin_Pick_Up_01": {
      "start": 83.1,
      "end": 83.32587301587301,
      "loop": false
    },
    "/sfx_Coin_Pick_Up/sfx_Coin_Pick_Up_02": {
      "start": 84.2,
      "end": 84.43297052154195,
      "loop": false
    },
    "/sfx_Coin_Pick_Up/sfx_Coin_Pick_Up_03": {
      "start": 85.3,
      "end": 85.60650793650794,
      "loop": false
    },
    "/sfx_Coin_Pick_Up/sfx_Coin_Pick_Up_04": {
      "start": 86.4,
      "end": 86.64,
      "loop": false
    },
    "/sfx_Coin_Pick_Up/sfx_Coin_Pick_Up_05": {
      "start": 87.5,
      "end": 87.751768707483,
      "loop": false
    },
    "/sfx_Dash/sfx_Dash_01": {
      "start": 88.60000000000001,
      "end": 88.86734693877551,
      "loop": false
    },
    "/sfx_Dash/sfx_Dash_02": {
      "start": 89.7,
      "end": 89.96385487528345,
      "loop": false
    },
    "/sfx_Dash/sfx_Dash_03": {
      "start": 90.8,
      "end": 91.07092970521542,
      "loop": false
    },
    "/sfx_Dash/sfx_Dash_04": {
      "start": 91.9,
      "end": 92.2018820861678,
      "loop": false
    },
    "/sfx_Footsteps/sfx_Footsteps_01": {
      "start": 93,
      "end": 93.12512471655329,
      "loop": false
    },
    "/sfx_Footsteps/sfx_Footsteps_02": {
      "start": 94.1,
      "end": 94.28367346938775,
      "loop": false
    },
    "/sfx_Footsteps/sfx_Footsteps_03": {
      "start": 95.19999999999999,
      "end": 95.36598639455781,
      "loop": false
    },
    "/sfx_Footsteps/sfx_Footsteps_04": {
      "start": 96.29999999999998,
      "end": 96.47972789115644,
      "loop": false
    },
    "/sfx_Footsteps/sfx_Footsteps_05": {
      "start": 97.39999999999998,
      "end": 97.62299319727889,
      "loop": false
    },
    "/sfx_Footsteps/sfx_Footsteps_06": {
      "start": 98.49999999999997,
      "end": 98.65052154195008,
      "loop": false
    },
    "/sfx_Footsteps/sfx_Footsteps_07": {
      "start": 99.59999999999997,
      "end": 99.79360544217684,
      "loop": false
    },
    "/sfx_Footsteps/sfx_Footsteps_08": {
      "start": 100.69999999999997,
      "end": 100.86970521541947,
      "loop": false
    },
    "/sfx_Footsteps/sfx_Footsteps_09": {
      "start": 101.79999999999997,
      "end": 101.97394557823127,
      "loop": false
    },
    "/sfx_Footsteps/sfx_Footsteps_10": {
      "start": 102.89999999999998,
      "end": 103.05512471655327,
      "loop": false
    },
    "/sfx_Footsteps/sfx_Footsteps_11": {
      "start": 103.99999999999997,
      "end": 104.2108616780045,
      "loop": false
    },
    "/sfx_Footsteps/sfx_Footsteps_12": {
      "start": 105.09999999999997,
      "end": 105.29024943310654,
      "loop": false
    },
    "/sfx_Footsteps/sfx_Footsteps_13": {
      "start": 106.19999999999996,
      "end": 106.36877551020405,
      "loop": false
    },
    "/sfx_Footsteps/sfx_Footsteps_14": {
      "start": 107.29999999999997,
      "end": 107.49142857142854,
      "loop": false
    },
    "/sfx_Footsteps/sfx_Footsteps_15": {
      "start": 108.39999999999998,
      "end": 108.58047619047616,
      "loop": false
    },
    "/sfx_Footsteps/sfx_Footsteps_16": {
      "start": 109.49999999999997,
      "end": 109.65999999999997,
      "loop": false
    },
    "/sfx_Footsteps/sfx_Footsteps_17": {
      "start": 110.59999999999997,
      "end": 110.79408163265303,
      "loop": false
    },
    "/sfx_Footsteps/sfx_Footsteps_18": {
      "start": 111.69999999999997,
      "end": 111.87092970521539,
      "loop": false
    },
    "/sfx_Footsteps/sfx_Footsteps_19": {
      "start": 112.79999999999997,
      "end": 112.98882086167798,
      "loop": false
    },
    "/sfx_Footsteps/sfx_Footsteps_20": {
      "start": 113.89999999999998,
      "end": 114.09077097505667,
      "loop": false
    },
    "/sfx_Footsteps/sfx_Footsteps_21": {
      "start": 114.99999999999999,
      "end": 115.22666666666666,
      "loop": false
    },
    "/sfx_Footsteps/sfx_Footsteps_22": {
      "start": 116.1,
      "end": 116.24786848072561,
      "loop": false
    },
    "/sfx_Footsteps/sfx_Footsteps_23": {
      "start": 117.19999999999999,
      "end": 117.39269841269841,
      "loop": false
    },
    "/sfx_Footsteps/sfx_Footsteps_24": {
      "start": 118.3,
      "end": 118.47126984126984,
      "loop": false
    },
    "/sfx_Footsteps/sfx_Footsteps_25": {
      "start": 119.4,
      "end": 119.58326530612246,
      "loop": false
    },
    "/sfx_Footsteps/sfx_Footsteps_26": {
      "start": 120.50000000000001,
      "end": 120.66378684807258,
      "loop": false
    },
    "/sfx_Footsteps/sfx_Footsteps_27": {
      "start": 121.60000000000001,
      "end": 121.81591836734695,
      "loop": false
    },
    "/sfx_Footsteps/sfx_Footsteps_28": {
      "start": 122.70000000000002,
      "end": 122.89210884353743,
      "loop": false
    },
    "/sfx_Footsteps/sfx_Footsteps_29": {
      "start": 123.80000000000001,
      "end": 123.96938775510205,
      "loop": false
    },
    "/sfx_Footsteps/sfx_Footsteps_30": {
      "start": 124.9,
      "end": 125.09167800453515,
      "loop": false
    },
    "/sfx_Footsteps/sfx_Footsteps_31": {
      "start": 126,
      "end": 126.1834693877551,
      "loop": false
    },
    "/sfx_Footsteps/sfx_Footsteps_32": {
      "start": 127.1,
      "end": 127.26637188208616,
      "loop": false
    },
    "/sfx_Footsteps/sfx_Footsteps_33": {
      "start": 128.2,
      "end": 128.3891156462585,
      "loop": false
    },
    "/sfx_Footsteps/sfx_Footsteps_34": {
      "start": 129.29999999999998,
      "end": 129.46977324263037,
      "loop": false
    },
    "/sfx_Footsteps/sfx_Footsteps_35": {
      "start": 130.39999999999998,
      "end": 130.59142857142854,
      "loop": false
    },
    "/sfx_Footsteps/sfx_Footsteps_36": {
      "start": 131.49999999999997,
      "end": 131.6904535147392,
      "loop": false
    },
    "/sfx_Footsteps/sfx_Footsteps_37": {
      "start": 132.59999999999997,
      "end": 132.8286167800453,
      "loop": false
    },
    "/sfx_Footsteps/sfx_Footsteps_38": {
      "start": 133.69999999999996,
      "end": 133.84430839002263,
      "loop": false
    },
    "/sfx_Footsteps/sfx_Footsteps_39": {
      "start": 134.79999999999995,
      "end": 134.98564625850335,
      "loop": false
    },
    "/sfx_Glorb/sfx_Glorb_Power_Up_01": {
      "start": 135.89999999999995,
      "end": 139.51564625850335,
      "loop": false
    },
    "/sfx_Glorb/sfx_Glorb_Power_Up_02": {
      "start": 139.99999999999994,
      "end": 143.50260770975052,
      "loop": false
    },
    "/sfx_Glorb/sfx_Glorb_Power_Up_03": {
      "start": 144.09999999999997,
      "end": 148.09999999999997,
      "loop": false
    },
    "/sfx_Jethro_Dash/sfx_Jethro_Dash_01": {
      "start": 148.19999999999996,
      "end": 148.5197959183673,
      "loop": false
    },
    "/sfx_Jethro_Dash/sfx_Jethro_Dash_02": {
      "start": 149.29999999999995,
      "end": 149.6333333333333,
      "loop": false
    },
    "/sfx_Jethro_Dash/sfx_Jethro_Dash_03": {
      "start": 150.39999999999998,
      "end": 150.73333333333332,
      "loop": false
    },
    "/sfx_Jethro_Tracks/sfx_Jethro_Tracks_01": {
      "start": 151.5,
      "end": 156.0541723356009,
      "loop": false
    },
    "/sfx_Jethro_Tracks/sfx_Jethro_Tracks_02": {
      "start": 156.6,
      "end": 160.8677097505669,
      "loop": false
    },
    "/sfx_Jethro_Tracks/sfx_Jethro_Tracks_03": {
      "start": 161.7,
      "end": 166.1661678004535,
      "loop": false
    },
    "/sfx_Jethro_Tracks/sfx_Jethro_Tracks_04": {
      "start": 166.79999999999998,
      "end": 171.14272108843537,
      "loop": false
    },
    "/sfx_Jethro_Tracks_Loop/sfx_Jethro_Tracks_Loop_01": {
      "start": 171.9,
      "end": 180.52501133786848,
      "loop": false
    },
    "/sfx_Jethro_Tracks_Loop/sfx_Jethro_Tracks_Loop_02": {
      "start": 181,
      "end": 192.33689342403628,
      "loop": false
    },
    "/sfx_Make_Purchase/sfx_Make_Purchase_01": {
      "start": 193.1,
      "end": 193.96471655328799,
      "loop": false
    },
    "/sfx_Make_Purchase/sfx_Make_Purchase_02": {
      "start": 194.20000000000002,
      "end": 195.064716553288,
      "loop": false
    },
    "/sfx_Make_Purchase/sfx_Make_Purchase_03": {
      "start": 195.30000000000004,
      "end": 196.16859410430843,
      "loop": false
    },
    "/sfx_Punch/sfx_Punch_01": {
      "start": 196.40000000000003,
      "end": 197.25000000000003,
      "loop": false
    },
    "/sfx_Punch/sfx_Punch_02": {
      "start": 197.50000000000003,
      "end": 198.22501133786852,
      "loop": false
    },
    "/sfx_Punch/sfx_Punch_03": {
      "start": 198.60000000000005,
      "end": 199.2703174603175,
      "loop": false
    },
    "/sfx_Punch/sfx_Punch_04": {
      "start": 199.70000000000005,
      "end": 200.82224489795922,
      "loop": false
    },
    "/sfx_Take_Damage/sfx_KO_Take_Damage_01": {
      "start": 201.80000000000004,
      "end": 202.53022675736966,
      "loop": false
    },
    "/sfx_Take_Damage/sfx_KO_Take_Damage_02": {
      "start": 202.90000000000003,
      "end": 203.63897959183677,
      "loop": false
    },
    "/sfx_Take_Damage/sfx_KO_Take_Damage_03": {
      "start": 204.00000000000003,
      "end": 204.63594104308393,
      "loop": false
    },
    "/sfx_Take_Damage/sfx_KO_Take_Damage_04": {
      "start": 205.10000000000002,
      "end": 205.98882086167802,
      "loop": false
    },
    "/sfx_Take_Damage_Alarm/sfx_Take_Damage_Alarm": {
      "start": 206.20000000000002,
      "end": 210.82519274376418,
      "loop": false
    },
    "/sfx_Take_Damage_GameOver/sfx_KO_Take_Damage_Game_Over": {
      "start": 211.3,
      "end": 213.3265986394558,
      "loop": false
    },
    "/sfx_Take_Damage_Music/sfx_Take_Damage_Music_01": {
      "start": 214.4,
      "end": 217.22625850340137,
      "loop": false
    },
    "/sfx_Take_Damage_Music/sfx_Take_Damage_Music_02": {
      "start": 217.5,
      "end": 220.0289569160998,
      "loop": false
    },
    "/sfx_Take_Damage_Music/sfx_Take_Damage_Music_03": {
      "start": 220.60000000000002,
      "end": 223.20000000000002,
      "loop": false
    },
    "/ui_Mouse_Click/ui_Mouse_Click_01": {
      "start": 223.70000000000002,
      "end": 223.76954648526078,
      "loop": false
    },
    "/ui_Mouse_Click/ui_Mouse_Click_02": {
      "start": 224.8,
      "end": 224.8667120181406,
      "loop": false
    },
    "/ui_Mouse_Click/ui_Mouse_Click_03": {
      "start": 225.9,
      "end": 225.94448979591837,
      "loop": false
    },
    "/ui_Mouse_Hover/ui_Mouse_Hover": {
      "start": 227,
      "end": 227.10748299319727,
      "loop": false
    },
    "/ui_Pop_Up_Expand/ui_Pop_Up_Expand": {
      "start": 228.1,
      "end": 229.39800453514738,
      "loop": false
    },
    "/ui_Pop_Up_Expand/ui_Pop_Up_Expand_02": {
      "start": 230.2,
      "end": 230.46936507936508,
      "loop": false
    },
    "/ui_Pop_Up_Expand/ui_Pop_Up_Expand_03": {
      "start": 231.29999999999998,
      "end": 231.704693877551,
      "loop": false
    },
    "/ui_Pop_Up_Minimize/ui_Pop_Up_Minimize": {
      "start": 232.39999999999998,
      "end": 233.06285714285713,
      "loop": false
    },
    "/ui_Pop_Up_Minimize/ui_Pop_Up_Minimize_02": {
      "start": 233.49999999999997,
      "end": 233.82058956916097,
      "loop": false
    },
    "/voice_Enid/voice_Go_go_go": {
      "start": 234.59999999999997,
      "end": 235.83061224489794,
      "loop": false
    },
    "/voice_KO/voice_Dash/voice_Dash_01": {
      "start": 236.7,
      "end": 237.25990929705213,
      "loop": false
    },
    "/voice_KO/voice_Dash/voice_Dash_02": {
      "start": 237.79999999999998,
      "end": 238.13058956916097,
      "loop": false
    },
    "/voice_KO/voice_Dash/voice_Dash_03": {
      "start": 238.89999999999998,
      "end": 239.19167800453513,
      "loop": false
    },
    "/voice_KO/voice_Dash/voice_Dash_04": {
      "start": 240,
      "end": 240.29167800453516,
      "loop": false
    },
    "/voice_KO/voice_Dash/voice_Dash_05": {
      "start": 241.10000000000002,
      "end": 241.32351473922904,
      "loop": false
    },
    "/voice_KO/voice_Glorb/voice_Glorb_01": {
      "start": 242.20000000000002,
      "end": 243.63911564625852,
      "loop": false
    },
    "/voice_KO/voice_Glorb/voice_Glorb_02": {
      "start": 244.3,
      "end": 245.71024943310658,
      "loop": false
    },
    "/voice_KO/voice_Glorb/voice_Glorb_03": {
      "start": 246.4,
      "end": 247.61956916099774,
      "loop": false
    },
    "/voice_KO/voice_Glorb/voice_Glorb_04": {
      "start": 248.5,
      "end": 249.5,
      "loop": false
    }
  }
}