[{"template":{"key":"bottom_pickup","tags":["obstacle","pickup","general"]},"transform":{},"animation":{"pack":"sprites","asset":"pickup/patty.json","layer":"bottomPlayer","fps":6,"offset":{"x":50,"y":0}},"physics":{"shape":{"width":50,"height":50,"sensor":true},"offset":{"x":50,"y":0}},"collectable":{"amount":1,"collectedSound":"pickup_burger"}},{"template":{"key":"top_pickup","tags":["obstacle","pickup","general"]},"transform":{},"animation":{"pack":"sprites","asset":"pickup_top/patty_top.json","layer":"bottomPlayer","fps":6,"offset":{"x":50,"y":0}},"physics":{"shape":{"width":50,"height":50,"sensor":true},"offset":{"x":50,"y":0}},"collectable":{"amount":1,"collectedSound":"pickup_burger"}},{"template":{"key":"invincible","tags":["obstacle","pickup","general"]},"transform":{},"animation":{"pack":"sprites","asset":"invincibility_pickup/pickup.json","layer":"bottomPlayer","fps":6,"offset":{"x":50,"y":0}},"physics":{"shape":{"width":50,"height":50,"sensor":true},"offset":{"x":50,"y":0}},"invinciblecollectable":{"collectedSound":"pickup_invulnerability"}}]
